rs_server_catalog/__init__.py
rs_server_catalog/authentication_catalog.py
rs_server_catalog/landing_page.py
rs_server_catalog/main.py
rs_server_catalog/response_manager.py
rs_server_catalog/timestamps_extension.py
rs_server_catalog/user_catalog.py
rs_server_catalog/user_handler.py
rs_server_catalog/utils.py
rs_server_catalog-99.99.dist-info/METADATA
rs_server_catalog-99.99.dist-info/WHEEL
rs_server_catalog-99.99.dist-info/RECORD
